AUTHORS.rst
CHANGELOG.rst
LICENSE
MANIFEST.in
README.rst
setup.py
jmbo_twitter/__init__.py
jmbo_twitter/admin.py
jmbo_twitter/admin_urls.py
jmbo_twitter/admin_views.py
jmbo_twitter/models.py
jmbo_twitter/tasks.py
jmbo_twitter/urls.py
jmbo_twitter.egg-info/PKG-INFO
jmbo_twitter.egg-info/SOURCES.txt
jmbo_twitter.egg-info/dependency_links.txt
jmbo_twitter.egg-info/not-zip-safe
jmbo_twitter.egg-info/requires.txt
jmbo_twitter.egg-info/top_level.txt
jmbo_twitter/migrations/0001_initial.py
jmbo_twitter/migrations/0001_initial.pyc
jmbo_twitter/migrations/0002_auto__add_field_feed_twitter_id.py
jmbo_twitter/migrations/0002_auto__add_field_feed_twitter_id.pyc
jmbo_twitter/migrations/0003_auto__add_search.py
jmbo_twitter/migrations/0003_auto__add_search.pyc
jmbo_twitter/migrations/__init__.py
jmbo_twitter/migrations/__init__.pyc
jmbo_twitter/templates/admin/jmbo_twitter/feed_tweets.html
jmbo_twitter/templates/jmbo_twitter/inclusion_tags/feed_detail.html
jmbo_twitter/templates/jmbo_twitter/inclusion_tags/feed_list_item_widget.html
jmbo_twitter/templates/jmbo_twitter/inclusion_tags/search_detail.html
jmbo_twitter/templates/jmbo_twitter/inclusion_tags/search_list_item_widget.html
jmbo_twitter/templates/jmbo_twitter/inclusion_tags/status_list_item_thumbnail.html
jmbo_twitter/templatetags/__init__.py
jmbo_twitter/templatetags/__init__.pyc
jmbo_twitter/templatetags/jmbo_twitter_tags.py
jmbo_twitter/templatetags/jmbo_twitter_tags.pyc
jmbo_twitter/tests/__init__.py
jmbo_twitter/tests/__init__.pyc
jmbo_twitter/tests/requirements.txt
jmbo_twitter/tests/urls.py
jmbo_twitter/tests/urls.pyc